edfi_canvas_extractor/__init__.py
edfi_canvas_extractor/__main__.py
edfi_canvas_extractor/client_graphql.py
edfi_canvas_extractor/config.py
edfi_canvas_extractor/extract_graphql.py
edfi_canvas_extractor/graphql/__init__.py
edfi_canvas_extractor/graphql/assignments.py
edfi_canvas_extractor/graphql/canvas.py
edfi_canvas_extractor/graphql/canvas_helper.py
edfi_canvas_extractor/graphql/canvas_object.py
edfi_canvas_extractor/graphql/courses.py
edfi_canvas_extractor/graphql/enrollments.py
edfi_canvas_extractor/graphql/extractor.py
edfi_canvas_extractor/graphql/schema.py
edfi_canvas_extractor/graphql/sections.py
edfi_canvas_extractor/graphql/students.py
edfi_canvas_extractor/graphql/submissions.py
edfi_canvas_extractor/graphql/utils.py
edfi_canvas_extractor/helpers/__init__.py
edfi_canvas_extractor/helpers/arg_parser.py
edfi_canvas_extractor/helpers/constants.py
edfi_canvas_extractor/mapping/__init__.py
edfi_canvas_extractor/mapping/assignments.py
edfi_canvas_extractor/mapping/constants.py
edfi_canvas_extractor/mapping/grades.py
edfi_canvas_extractor/mapping/helpers.py
edfi_canvas_extractor/mapping/section_associations.py
edfi_canvas_extractor/mapping/sections.py
edfi_canvas_extractor/mapping/submissions.py
edfi_canvas_extractor/mapping/users.py
edfi_canvas_extractor-2.0.2.dist-info/METADATA
edfi_canvas_extractor-2.0.2.dist-info/WHEEL
edfi_canvas_extractor-2.0.2.dist-info/RECORD
